pycolor/__init__.py
pycolor/main.py
pycolor_codern-1.1.dist-info/LICENSE
pycolor_codern-1.1.dist-info/METADATA
pycolor_codern-1.1.dist-info/WHEEL
pycolor_codern-1.1.dist-info/top_level.txt
pycolor_codern-1.1.dist-info/RECORD
