Metadata-Version: 2.1
Name: pycolor-codern
Version: 1.1
Summary: Pycolor uses thecolorapi to to get useful information about colors in a pythonic way.
Home-page: https://github.com/CoderN-P/pycolor
Author: Neel Parpia
Author-email: neel.parpia@gmail.com
License: MIT
Keywords: color,colorapi,python
Platform: UNKNOWN
Classifier: Development Status :: 4 - Beta
Classifier: Intended Audience :: Developers
Classifier: Topic :: Software Development :: Build Tools
Classifier: License :: OSI Approved :: MIT License
Classifier: Programming Language :: Python :: 3
Classifier: Programming Language :: Python :: 3.4
Classifier: Programming Language :: Python :: 3.5
Classifier: Programming Language :: Python :: 3.6
Classifier: Programming Language :: Python :: 3.7
Classifier: Programming Language :: Python :: 3.8
Classifier: Programming Language :: Python :: 3.9
License-File: LICENSE
